cleopatra/__init__.py
cleopatra/array_glyph.py
cleopatra/colors.py
cleopatra/config.py
cleopatra/statistical_glyph.py
cleopatra/styles.py
cleopatra-0.6.0.dist-info/licenses/AUTHORS.rst
cleopatra-0.6.0.dist-info/licenses/LICENSE.md
cleopatra-0.6.0.dist-info/METADATA
cleopatra-0.6.0.dist-info/WHEEL
cleopatra-0.6.0.dist-info/top_level.txt
cleopatra-0.6.0.dist-info/RECORD
